setup.py
cebsyldec/syllabledecoder.py
cebsyldec_package_eemberda-0.0.1.dist-info/METADATA
cebsyldec_package_eemberda-0.0.1.dist-info/WHEEL
cebsyldec_package_eemberda-0.0.1.dist-info/licenses/LICENSE
cebsyldec_package_eemberda-0.0.1.dist-info/RECORD
