Metadata-Version: 2.1
Name: cebsyldec_package_EEMBERDA
Version: 0.0.1
Summary: Decodes a Cebuano word into syllables
Project-URL: Homepage, https://github.com/eemberda/Cebuano-Syllable-Decoder
Project-URL: Bug Tracker, https://github.com/eemberda/Cebuano-Syllable-Decoder/issues
Author-email: Eric John Emberda <eric.emberda@gmail.com>
License-File: LICENSE
Classifier: License :: OSI Approved :: GNU General Public License v3 (GPLv3)
Classifier: Operating System :: OS Independent
Classifier: Programming Language :: Python :: 3
Requires-Python: >=3.7
